chpy/__init__.py
chpy/client.py
chpy/config.py
chpy/ddl.py
chpy/orm.py
chpy/query_builder.py
chpy/tables.py
chpy/types.py
chpy/functions/__init__.py
chpy/functions/aggregate.py
chpy/functions/arithmetic.py
chpy/functions/array.py
chpy/functions/base.py
chpy/functions/bitwise.py
chpy/functions/comparison.py
chpy/functions/conditional.py
chpy/functions/date_time.py
chpy/functions/encoding.py
chpy/functions/geo.py
chpy/functions/hash.py
chpy/functions/ip.py
chpy/functions/json.py
chpy/functions/logical.py
chpy/functions/map.py
chpy/functions/math.py
chpy/functions/nullable.py
chpy/functions/other.py
chpy/functions/rounding.py
chpy/functions/string.py
chpy/functions/tuple.py
chpy/functions/type_conversion.py
chpy/functions/url.py
chpy/functions/uuid.py
chpy/functions/window.py
chpy_orm-0.2.1.dist-info/licenses/LICENSE
tests/__init__.py
tests/conftest.py
tests/test_client.py
tests/test_config.py
tests/test_ddl.py
tests/test_ddl_advanced.py
tests/test_functions.py
tests/test_integration.py
tests/test_orm.py
tests/test_query_builder.py
tests/test_schema.py
tests/test_subqueries.py
tests/test_tables.py
tests/test_types.py
tests/test_window_functions.py
tests/test_window_query_integration.py
chpy_orm-0.2.1.dist-info/METADATA
chpy_orm-0.2.1.dist-info/WHEEL
chpy_orm-0.2.1.dist-info/top_level.txt
chpy_orm-0.2.1.dist-info/RECORD
